Workbook
Name Slicer_Month: #N/A
Name Slicer_Year: #N/A

Sheet PROJECT OVERVIEW
B1: Project Title
B2: Retail / Sales Performance Analysis
B4: Project Objective:
B5: This project analyzes the financial performance of Lizzy Electronics from 2021 to 2025, focusing on revenue trends, cost behaviour, profitability, and growth patterns.
B7: Scope of Analysis:
B8: The analysis covers the following to evaluate business sustainability and financial efficiency.
B9: · monthly and annual revenue
B10: · expenses
B11: · net profit
B12: · profit margins
B13: · growth rates
B15: Business Questions:
... B35: · Cost–revenue relationship

Sheet DASHBOARD
B2: FINANCIAL PERFORMANCE DASHBOARD 2021-2025
B4: TOTAL REVENUE | D4: TOTAL NET PROFIT | F4: TOTAL EXPENSES | H4: AVERAGE GROWTH RATE | J4: AVERAGE PROFIT MARGIN | L4: EXPENSES - REVENUE RATIO
B7: =SUM('PIVOT TABLES'!F4:F15) -> 73130000 | D7: =SUM('PIVOT TABLES'!G4:G15) -> 13234500 | F7: =SUM('PIVOT TABLES'!F18:F77) -> 15980500 | H7: 0.0202 | J7: =AVERAGE('CLEANED DATA'!K3:K66) -> 0.17767602 | L7: 0.2478

Sheet INSIGHTS
B1: Executive Summary
C3: This analysis evaluates the company's revenue, profitability, and expenses to understand financial performance and identify opportunities for improvement.
C5: Overall Performance
C6: The business demonstrates sustainable growth with controlled expenses and positive profitability trends.
C8: Revenue & Growth Trend
B9: 1 . | C9: Revenue shows a generally upward trend, indicating steady business expansion across the analysis period.
B10: 2 . | C10: Growth rate fluctuations suggest seasonal effects and varying market demand across months.
B11: 3 . | C11: The average monthly growth rate indicates moderate moderate expansion, but flunctuations in some months suggests unstable performance
C13: Expense Analysis
B14: 1 . | C14: Expenses are strongly correlated with revenue (correlation = 0.96), indicating that higher sales are associated with increased operational costs.
B15: 2 . | C15: Expense growth remains proportional, suggesting controlled cost management.
B16: 3 . | C16: Despite revenue groth, rising expenses are reducing overall profit margins
C18: Profitability
B19: 1 . | C19: Although revenue increased, net profits did not rise at the same rate, implying that rising expenses affects profitability.
B20: 2 . | C20: Net profit remains consistently below revenue due to cost structure, which is expected in retail operations.
B21: 3 . | C21: Profit margin varies across months, highlighting periods of higher operational efficiency.
C23: Business Recommendations
B24: 1 . | C24: Focus on high peforming months to understand demand drivers.
B25: 2 . | C25: Investigate expense category contributing most to revenue reduction.
B26: 3 . | C26: improve cost managements to stabilize profit margins.

Sheet CLEANED DATA
A1: LIZZY ELECTRONICS: FINANCIAL PERFORMANCE ANALYSIS (2021-2025)
A2: Year | B2: Month | C2: Revenue | D2: Cost Of Goods Sold | E2: Operating Expenses | F2: Marketing Expenses | G2: Other Expenses | H2: Gross Profit | I2: Total Expenses | J2: Net Profit | K2: Net Profit Margin (%) | L2: Monthly Growth Rate %
A3: 2021 | B3: Jan | C3: 850000 | D3: 510000 | E3: 140000 | F3: 45000 | G3: 30000 | H3: ='CLEANED DATA'!$C3-'CLEANED DATA'!$D3 -> 340000 | I3: ='CLEANED DATA'!$E3+'CLEANED DATA'!$F3+'CLEANED DATA'!$G3 -> 215000 | J3: ='CLEANED DATA'!$C3-('CLEANED DATA'!$D3+'CLEANED DATA'!$I3) -> 125000 | K3: ='CLEANED DATA'!$J3/'CLEANED DATA'!$C3 -> 0.14705882 | L3: N/A
A4: 2021 | B4: Feb | C4: 820000 | D4: 500000 | E4: 138000 | F4: 42000 | G4: 28000 | H4: ='CLEANED DATA'!$C4-'CLEANED DATA'!$D4 -> 320000 | I4: ='CLEANED DATA'!$E4+'CLEANED DATA'!$F4+'CLEANED DATA'!$G4 -> 208000 | J4: ='CLEANED DATA'!$C4-('CLEANED DATA'!$D4+'CLEANED DATA'!$I4) -> 112000 | K4: ='CLEANED DATA'!$J4/'CLEANED DATA'!$C4 -> 0.13658537 | L4: =('CLEANED DATA'!$C4-C3)/C3 -> -0.035294118
A5: 2021 | B5: Mar | C5: 900000 | D5: 540000 | E5: 145000 | F5: 47000 | G5: 31000 | H5: ='CLEANED DATA'!$C5-'CLEANED DATA'!$D5 -> 360000 | I5: ='CLEANED DATA'!$E5+'CLEANED DATA'!$F5+'CLEANED DATA'!$G5 -> 223000 | J5: ='CLEANED DATA'!$C5-('CLEANED DATA'!$D5+'CLEANED DATA'!$I5) -> 137000 | K5: ='CLEANED DATA'!$J5/'CLEANED DATA'!$C5 -> 0.15222222 | L5: =('CLEANED DATA'!$C5-C4)/C4 -> 0.097560976
A6: 2021 | B6: Apr | C6: 870000 | D6: 525000 | E6: 142000 | F6: 46000 | G6: 29500 | H6: ='CLEANED DATA'!$C6-'CLEANED DATA'!$D6 -> 345000 | I6: ='CLEANED DATA'!$E6+'CLEANED DATA'!$F6+'CLEANED DATA'!$G6 -> 217500 | J6: ='CLEANED DATA'!$C6-('CLEANED DATA'!$D6+'CLEANED DATA'!$I6) -> 127500 | K6: ='CLEANED DATA'!$J6/'CLEANED DATA'!$C6 -> 0.14655172 | L6: =('CLEANED DATA'!$C6-C5)/C5 -> -0.033333333
A7: 2021 | B7: May | C7: 920000 | D7: 550000 | E7: 148000 | F7: 48000 | G7: 32000 | H7: ='CLEANED DATA'!$C7-'CLEANED DATA'!$D7 -> 370000 | I7: ='CLEANED DATA'!$E7+'CLEANED DATA'!$F7+'CLEANED DATA'!$G7 -> 228000 | J7: ='CLEANED DATA'!$C7-('CLEANED DATA'!$D7+'CLEANED DATA'!$I7) -> 142000 | K7: ='CLEANED DATA'!$J7/'CLEANED DATA'!$C7 -> 0.15434783 | L7: =('CLEANED DATA'!$C7-C6)/C6 -> 0.057471264
A8: 2021 | B8: Jun | C8: 950000 | D8: 570000 | E8: 150000 | F8: 50000 | G8: 33000 | H8: ='CLEANED DATA'!$C8-'CLEANED DATA'!$D8 -> 380000 | I8: ='CLEANED DATA'!$E8+'CLEANED DATA'!$F8+'CLEANED DATA'!$G8 -> 233000 | J8: ='CLEANED DATA'!$C8-('CLEANED DATA'!$D8+'CLEANED DATA'!$I8) -> 147000 | K8: ='CLEANED DATA'!$J8/'CLEANED DATA'!$C8 -> 0.15473684 | L8: =('CLEANED DATA'!$C8-C7)/C7 -> 0.032608696
A9: 2021 | B9: Jul | C9: 980000 | D9: 590000 | E9: 152000 | F9: 52000 | G9: 35000 | H9: ='CLEANED DATA'!$C9-'CLEANED DATA'!$D9 -> 390000 | I9: ='CLEANED DATA'!$E9+'CLEANED DATA'!$F9+'CLEANED DATA'!$G9 -> 239000 | J9: ='CLEANED DATA'!$C9-('CLEANED DATA'!$D9+'CLEANED DATA'!$I9) -> 151000 | K9: ='CLEANED DATA'!$J9/'CLEANED DATA'!$C9 -> 0.15408163 | L9: =('CLEANED DATA'!$C9-C8)/C8 -> 0.031578947
A10: 2021 | B10: Aug | C10: 960000 | D10: 580000 | E10: 150000 | F10: 51000 | G10: 34000 | H10: ='CLEANED DATA'!$C10-'CLEANED DATA'!$D10 -> 380000 | I10: ='CLEANED DATA'!$E10+'CLEANED DATA'!$F10+'CLEANED DATA'!$G10 -> 235000 | J10: ='CLEANED DATA'!$C10-('CLEANED DATA'!$D10+'CLEANED DATA'!$I10) -> 145000 | K10: ='CLEANED DATA'!$J10/'CLEANED DATA'!$C10 -> 0.15104167 | L10: =('CLEANED DATA'!$C10-C9)/C9 -> -0.020408163
A11: 2021 | B11: Sep | C11: 1020000 | D11: 610000 | E11: 155000 | F11: 54000 | G11: 36000 | H11: ='CLEANED DATA'!$C11-'CLEANED DATA'!$D11 -> 410000 | I11: ='CLEANED DATA'!$E11+'CLEANED DATA'!$F11+'CLEANED DATA'!$G11 -> 245000 | J11: ='CLEANED DATA'!$C11-('CLEANED DATA'!$D11+'CLEANED DATA'!$I11) -> 165000 | K11: ='CLEANED DATA'!$J11/'CLEANED DATA'!$C11 -> 0.16176471 | L11: =('CLEANED DATA'!$C11-C10)/C10 -> 0.0625
A12: 2021 | B12: Oct | C12: 1080000 | D12: 650000 | E12: 160000 | F12: 58000 | G12: 38000 | H12: ='CLEANED DATA'!$C12-'CLEANED DATA'!$D12 -> 430000 | I12: ='CLEANED DATA'!$E12+'CLEANED DATA'!$F12+'CLEANED DATA'!$G12 -> 256000 | J12: ='CLEANED DATA'!$C12-('CLEANED DATA'!$D12+'CLEANED DATA'!$I12) -> 174000 | K12: ='CLEANED DATA'!$J12/'CLEANED DATA'!$C12 -> 0.16111111 | L12: =('CLEANED DATA'!$C12-C11)/C11 -> 0.058823529
A13: 2021 | B13: Nov | C13: 1150000 | D13: 690000 | E13: 165000 | F13: 62000 | G13: 40000 | H13: ='CLEANED DATA'!$C13-'CLEANED DATA'!$D13 -> 460000 | I13: ='CLEANED DATA'!$E13+'CLEANED DATA'!$F13+'CLEANED DATA'!$G13 -> 267000 | J13: ='CLEANED DATA'!$C13-('CLEANED DATA'!$D13+'CLEANED DATA'!$I13) -> 193000 | K13: ='CLEANED DATA'!$J13/'CLEANED DATA'!$C13 -> 0.16782609 | L13: =('CLEANED DATA'!$C13-C12)/C12 -> 0.064814815
A14: 2021 | B14: Dec | C14: 1300000 | D14: 780000 | E14: 175000 | F14: 70000 | G14: 45000 | H14: ='CLEANED DATA'!$C14-'CLEANED DATA'!$D14 -> 520000 | I14: ='CLEANED DATA'!$E14+'CLEANED DATA'!$F14+'CLEANED DATA'!$G14 -> 290000 | J14: ='CLEANED DATA'!$C14-('CLEANED DATA'!$D14+'CLEANED DATA'!$I14) -> 230000 | K14: ='CLEANED DATA'!$J14/'CLEANED DATA'!$C14 -> 0.17692308 | L14: =('CLEANED DATA'!$C14-C13)/C13 -> 0.13043478
A15: 2021 Total | C15: =SUBTOTAL(9,C3:C14) -> 11800000 | D15: =SUBTOTAL(9,D3:D14) -> 7095000 | E15: =SUBTOTAL(9,E3:E14) -> 1820000 | F15: =SUBTOTAL(9,F3:F14) -> 625000 | G15: =SUBTOTAL(9,G3:G14) -> 411500 | H15: =SUBTOTAL(9,H3:H14) -> 4705000 | I15: =SUBTOTAL(9,I3:I14) -> 2856500 | J15: =SUBTOTAL(9,J3:J14) -> 1848500
A16: 2022 | B16: Jan | C16: 920000 | D16: 550000 | E16: 145000 | F16: 47000 | G16: 32000 | H16: ='CLEANED DATA'!$C16-'CLEANED DATA'!$D16 -> 370000 | I16: ='CLEANED DATA'!$E16+'CLEANED DATA'!$F16+'CLEANED DATA'!$G16 -> 224000 | J16: ='CLEANED DATA'!$C16-('CLEANED DATA'!$D16+'CLEANED DATA'!$I16) -> 146000 | K16: ='CLEANED DATA'!$J16/'CLEANED DATA'!$C16 -> 0.15869565 | L16: =('CLEANED DATA'!$C16-C14)/C14 -> -0.29230769
A17: 2022 | B17: Feb | C17: 900000 | D17: 540000 | E17: 142000 | F17: 45000 | G17: 30000 | H17: ='CLEANED DATA'!$C17-'CLEANED DATA'!$D17 -> 360000 | I17: ='CLEANED DATA'!$E17+'CLEANED DATA'!$F17+'CLEANED DATA'!$G17 -> 217000 | J17: ='CLEANED DATA'!$C17-('CLEANED DATA'!$D17+'CLEANED DATA'!$I17) -> 143000 | K17: ='CLEANED DATA'!$J17/'CLEANED DATA'!$C17 -> 0.15888889 | L17: =('CLEANED DATA'!$C17-C16)/C16 -> -0.02173913
A18: 2022 | B18: Mar | C18: 980000 | D18: 590000 | E18: 148000 | F18: 49000 | G18: 34000 | H18: ='CLEANED DATA'!$C18-'CLEANED DATA'!$D18 -> 390000 | I18: ='CLEANED DATA'!$E18+'CLEANED DATA'!$F18+'CLEANED DATA'!$G18 -> 231000 | J18: ='CLEANED DATA'!$C18-('CLEANED DATA'!$D18+'CLEANED DATA'!$I18) -> 159000 | K18: ='CLEANED DATA'!$J18/'CLEANED DATA'!$C18 -> 0.1622449 | L18: =('CLEANED DATA'!$C18-C17)/C17 -> 0.088888889
A19: 2022 | B19: Apr | C19: 1010000 | D19: 610000 | E19: 150000 | F19: 52000 | G19: 36000 | H19: ='CLEANED DATA'!$C19-'CLEANED DATA'!$D19 -> 400000 | I19: ='CLEANED DATA'!$E19+'CLEANED DATA'!$F19+'CLEANED DATA'!$G19 -> 238000 | J19: ='CLEANED DATA'!$C19-('CLEANED DATA'!$D19+'CLEANED DATA'!$I19) -> 162000 | K19: ='CLEANED DATA'!$J19/'CLEANED DATA'!$C19 -> 0.16039604 | L19: =('CLEANED DATA'!$C19-C18)/C18 -> 0.030612245
A20: 2022 | B20: May | C20: 1060000 | D20: 640000 | E20: 155000 | F20: 55000 | G20: 38000 | H20: ='CLEANED DATA'!$C20-'CLEANED DATA'!$D20 -> 420000 | I20: ='CLEANED DATA'!$E20+'CLEANED DATA'!$F20+'CLEANED DATA'!$G20 -> 248000 | J20: ='CLEANED DATA'!$C20-('CLEANED DATA'!$D20+'CLEANED DATA'!$I20) -> 172000 | K20: ='CLEANED DATA'!$J20/'CLEANED DATA'!$C20 -> 0.16226415 | L20: =('CLEANED DATA'!$C20-C19)/C19 -> 0.04950495
A21: 2022 | B21: Jun | C21: 1100000 | D21: 660000 | E21: 158000 | F21: 58000 | G21: 40000 | H21: ='CLEANED DATA'!$C21-'CLEANED DATA'!$D21 -> 440000 | I21: ='CLEANED DATA'!$E21+'CLEANED DATA'!$F21+'CLEANED DATA'!$G21 -> 256000 | J21: ='CLEANED DATA'!$C21-('CLEANED DATA'!$D21+'CLEANED DATA'!$I21) -> 184000 | K21: ='CLEANED DATA'!$J21/'CLEANED DATA'!$C21 -> 0.16727273 | L21: =('CLEANED DATA'!$C21-C20)/C20 -> 0.037735849
A22: 2022 | B22: Jul | C22: 1140000 | D22: 690000 | E22: 160000 | F22: 60000 | G22: 42000 | H22: ='CLEANED DATA'!$C22-'CLEANED DATA'!$D22 -> 450000 | I22: ='CLEANED DATA'!$E22+'CLEANED DATA'!$F22+'CLEANED DATA'!$G22 -> 262000 | J22: ='CLEANED DATA'!$C22-('CLEANED DATA'!$D22+'CLEANED DATA'!$I22) -> 188000 | K22: ='CLEANED DATA'!$J22/'CLEANED DATA'!$C22 -> 0.16491228 | L22: =('CLEANED DATA'!$C22-C21)/C21 -> 0.036363636
A23: 2022 | B23: Aug | C23: 1120000 | D23: 680000 | E23: 158000 | F23: 59000 | G23: 41000 | H23: ='CLEANED DATA'!$C23-'CLEANED DATA'!$D23 -> 440000 | I23: ='CLEANED DATA'!$E23+'CLEANED DATA'!$F23+'CLEANED DATA'!$G23 -> 258000 | J23: ='CLEANED DATA'!$C23-('CLEANED DATA'!$D23+'CLEANED DATA'!$I23) -> 182000 | K23: ='CLEANED DATA'!$J23/'CLEANED DATA'!$C23 -> 0.1625 | L23: =('CLEANED DATA'!$C23-C22)/C22 -> -0.01754386
A24: 2022 | B24: Sep | C24: 1180000 | D24: 710000 | E24: 162000 | F24: 63000 | G24: 44000 | H24: ='CLEANED DATA'!$C24-'CLEANED DATA'!$D24 -> 470000 | I24: ='CLEANED DATA'!$E24+'CLEANED DATA'!$F24+'CLEANED DATA'!$G24 -> 269000 | J24: ='CLEANED DATA'!$C24-('CLEANED DATA'!$D24+'CLEANED DATA'!$I24) -> 201000 | K24: ='CLEANED DATA'!$J24/'CLEANED DATA'!$C24 -> 0.17033898 | L24: =('CLEANED DATA'!$C24-C23)/C23 -> 0.053571429
A25: 2022 | B25: Oct | C25: 1250000 | D25: 750000 | E25: 168000 | F25: 68000 | G25: 47000 | H25: ='CLEANED DATA'!$C25-'CLEANED DATA'!$D25 -> 500000 | I25: ='CLEANED DATA'!$E25+'CLEANED DATA'!$F25+'CLEANED DATA'!$G25 -> 283000 | J25: ='CLEANED DATA'!$C25-('CLEANED DATA'!$D25+'CLEANED DATA'!$I25) -> 217000 | K25: ='CLEANED DATA'!$J25/'CLEANED DATA'!$C25 -> 0.1736 | L25: =('CLEANED DATA'!$C25-C24)/C24 -> 0.059322034
A26: 2022 | B26: Nov | C26: 1320000 | D26: 790000 | E26: 172000 | F26: 72000 | G26: 50000 | H26: ='CLEANED DATA'!$C26-'CLEANED DATA'!$D26 -> 530000 | I26: ='CLEANED DATA'!$E26+'CLEANED DATA'!$F26+'CLEANED DATA'!$G26 -> 294000 | J26: ='CLEANED DATA'!$C26-('CLEANED DATA'!$D26+'CLEANED DATA'!$I26) -> 236000 | K26: ='CLEANED DATA'!$J26/'CLEANED DATA'!$C26 -> 0.17878788 | L26: =('CLEANED DATA'!$C26-C25)/C25 -> 0.056
A27: 2022 | B27: Dec | C27: 1480000 | D27: 880000 | E27: 180000 | F27: 80000 | G27: 56000 | H27: ='CLEANED DATA'!$C27-'CLEANED DATA'!$D27 -> 600000 | I27: ='CLEANED DATA'!$E27+'CLEANED DATA'!$F27+'CLEANED DATA'!$G27 -> 316000 | J27: ='CLEANED DATA'!$C27-('CLEANED DATA'!$D27+'CLEANED DATA'!$I27) -> 284000 | K27: ='CLEANED DATA'!$J27/'CLEANED DATA'!$C27 -> 0.19189189 | L27: =('CLEANED DATA'!$C27-C26)/C26 -> 0.12121212
A28: 2022 Total | C28: =SUBTOTAL(9,C16:C27) -> 13460000 | D28: =SUBTOTAL(9,D16:D27) -> 8090000 | E28: =SUBTOTAL(9,E16:E27) -> 1898000 | F28: =SUBTOTAL(9,F16:F27) -> 708000 | G28: =SUBTOTAL(9,G16:G27) -> 490000 | H28: =SUBTOTAL(9,H16:H27) -> 5370000 | I28: =SUBTOTAL(9,I16:I27) -> 3096000 | J28: =SUBTOTAL(9,J16:J27) -> 2274000
A29: 2023 | B29: Jan | C29: 1050000 | D29: 630000 | E29: 150000 | F29: 52000 | G29: 36000 | H29: ='CLEANED DATA'!$C29-'CLEANED DATA'!$D29 -> 420000 | I29: ='CLEANED DATA'!$E29+'CLEANED DATA'!$F29+'CLEANED DATA'!$G29 -> 238000 | J29: ='CLEANED DATA'!$C29-('CLEANED DATA'!$D29+'CLEANED DATA'!$I29) -> 182000 | K29: ='CLEANED DATA'!$J29/'CLEANED DATA'!$C29 -> 0.17333333 | L29: =('CLEANED DATA'!$C29-C27)/C27 -> -0.29054054
A30: 2023 | B30: Feb | C30: 1020000 | D30: 620000 | E30: 148000 | F30: 50000 | G30: 34000 | H30: ='CLEANED DATA'!$C30-'CLEANED DATA'!$D30 -> 400000 | I30: ='CLEANED DATA'!$E30+'CLEANED DATA'!$F30+'CLEANED DATA'!$G30 -> 232000 | J30: ='CLEANED DATA'!$C30-('CLEANED DATA'!$D30+'CLEANED DATA'!$I30) -> 168000 | K30: ='CLEANED DATA'!$J30/'CLEANED DATA'!$C30 -> 0.16470588 | L30: =('CLEANED DATA'!$C30-C29)/C29 -> -0.028571429
A31: 2023 | B31: Mar | C31: 1100000 | D31: 660000 | E31: 152000 | F31: 54000 | G31: 38000 | H31: ='CLEANED DATA'!$C31-'CLEANED DATA'!$D31 -> 440000 | I31: ='CLEANED DATA'!$E31+'CLEANED DATA'!$F31+'CLEANED DATA'!$G31 -> 244000 | J31: ='CLEANED DATA'!$C31-('CLEANED DATA'!$D31+'CLEANED DATA'!$I31) -> 196000 | K31: ='CLEANED DATA'!$J31/'CLEANED DATA'!$C31 -> 0.17818182 | L31: =('CLEANED DATA'!$C31-C30)/C30 -> 0.078431373
A32: 2023 | B32: Apr | C32: 1140000 | D32: 680000 | E32: 155000 | F32: 56000 | G32: 40000 | H32: ='CLEANED DATA'!$C32-'CLEANED DATA'!$D32 -> 460000 | I32: ='CLEANED DATA'!$E32+'CLEANED DATA'!$F32+'CLEANED DATA'!$G32 -> 251000 | J32: ='CLEANED DATA'!$C32-('CLEANED DATA'!$D32+'CLEANED DATA'!$I32) -> 209000 | K32: ='CLEANED DATA'!$J32/'CLEANED DATA'!$C32 -> 0.18333333 | L32: =('CLEANED DATA'!$C32-C31)/C31 -> 0.036363636
A33: 2023 | B33: May | C33: 1180000 | D33: 710000 | E33: 158000 | F33: 59000 | G33: 42000 | H33: ='CLEANED DATA'!$C33-'CLEANED DATA'!$D33 -> 470000 | I33: ='CLEANED DATA'!$E33+'CLEANED DATA'!$F33+'CLEANED DATA'!$G33 -> 259000 | J33: ='CLEANED DATA'!$C33-('CLEANED DATA'!$D33+'CLEANED DATA'!$I33) -> 211000 | K33: ='CLEANED DATA'!$J33/'CLEANED DATA'!$C33 -> 0.17881356 | L33: =('CLEANED DATA'!$C33-C32)/C32 -> 0.035087719
A34: 2023 | B34: Jun | C34: 1220000 | D34: 730000 | E34: 160000 | F34: 62000 | G34: 44000 | H34: ='CLEANED DATA'!$C34-'CLEANED DATA'!$D34 -> 490000 | I34: ='CLEANED DATA'!$E34+'CLEANED DATA'!$F34+'CLEANED DATA'!$G34 -> 266000 | J34: ='CLEANED DATA'!$C34-('CLEANED DATA'!$D34+'CLEANED DATA'!$I34) -> 224000 | K34: ='CLEANED DATA'!$J34/'CLEANED DATA'!$C34 -> 0.18360656 | L34: =('CLEANED DATA'!$C34-C33)/C33 -> 0.033898305
A35: 2023 | B35: Jul | C35: 1270000 | D35: 760000 | E35: 162000 | F35: 65000 | G35: 47000 | H35: ='CLEANED DATA'!$C35-'CLEANED DATA'!$D35 -> 510000 | I35: ='CLEANED DATA'!$E35+'CLEANED DATA'!$F35+'CLEANED DATA'!$G35 -> 274000 | J35: ='CLEANED DATA'!$C35-('CLEANED DATA'!$D35+'CLEANED DATA'!$I35) -> 236000 | K35: ='CLEANED DATA'!$J35/'CLEANED DATA'!$C35 -> 0.18582677 | L35: =('CLEANED DATA'!$C35-C34)/C34 -> 0.040983607
A36: 2023 | B36: Aug | C36: 1250000 | D36: 750000 | E36: 160000 | F36: 64000 | G36: 46000 | H36: ='CLEANED DATA'!$C36-'CLEANED DATA'!$D36 -> 500000 | I36: ='CLEANED DATA'!$E36+'CLEANED DATA'!$F36+'CLEANED DATA'!$G36 -> 270000 | J36: ='CLEANED DATA'!$C36-('CLEANED DATA'!$D36+'CLEANED DATA'!$I36) -> 230000 | K36: ='CLEANED DATA'!$J36/'CLEANED DATA'!$C36 -> 0.184 | L36: =('CLEANED DATA'!$C36-C35)/C35 -> -0.015748031
A37: 2023 | B37: Sep | C37: 1320000 | D37: 790000 | E37: 165000 | F37: 68000 | G37: 50000 | H37: ='CLEANED DATA'!$C37-'CLEANED DATA'!$D37 -> 530000 | I37: ='CLEANED DATA'!$E37+'CLEANED DATA'!$F37+'CLEANED DATA'!$G37 -> 283000 | J37: ='CLEANED DATA'!$C37-('CLEANED DATA'!$D37+'CLEANED DATA'!$I37) -> 247000 | K37: ='CLEANED DATA'!$J37/'CLEANED DATA'!$C37 -> 0.18712121 | L37: =('CLEANED DATA'!$C37-C36)/C36 -> 0.056
A38: 2023 | B38: Oct | C38: 1380000 | D38: 830000 | E38: 170000 | F38: 72000 | G38: 53000 | H38: ='CLEANED DATA'!$C38-'CLEANED DATA'!$D38 -> 550000 | I38: ='CLEANED DATA'!$E38+'CLEANED DATA'!$F38+'CLEANED DATA'!$G38 -> 295000 | J38: ='CLEANED DATA'!$C38-('CLEANED DATA'!$D38+'CLEANED DATA'!$I38) -> 255000 | K38: ='CLEANED DATA'!$J38/'CLEANED DATA'!$C38 -> 0.18478261 | L38: =('CLEANED DATA'!$C38-C37)/C37 -> 0.045454545
A39: 2023 | B39: Nov | C39: 1450000 | D39: 870000 | E39: 175000 | F39: 76000 | G39: 56000 | H39: ='CLEANED DATA'!$C39-'CLEANED DATA'!$D39 -> 580000 | I39: ='CLEANED DATA'!$E39+'CLEANED DATA'!$F39+'CLEANED DATA'!$G39 -> 307000 | J39: ='CLEANED DATA'!$C39-('CLEANED DATA'!$D39+'CLEANED DATA'!$I39) -> 273000 | K39: ='CLEANED DATA'!$J39/'CLEANED DATA'!$C39 -> 0.18827586 | L39: =('CLEANED DATA'!$C39-C38)/C38 -> 0.050724638
A40: 2023 | B40: Dec | C40: 1620000 | D40: 960000 | E40: 185000 | F40: 85000 | G40: 62000 | H40: ='CLEANED DATA'!$C40-'CLEANED DATA'!$D40 -> 660000 | I40: ='CLEANED DATA'!$E40+'CLEANED DATA'!$F40+'CLEANED DATA'!$G40 -> 332000 | J40: ='CLEANED DATA'!$C40-('CLEANED DATA'!$D40+'CLEANED DATA'!$I40) -> 328000 | K40: ='CLEANED DATA'!$J40/'CLEANED DATA'!$C40 -> 0.20246914 | L40: =('CLEANED DATA'!$C40-C39)/C39 -> 0.11724138
A41: 2023 Total | C41: =SUBTOTAL(9,C29:C40) -> 15000000 | D41: =SUBTOTAL(9,D29:D40) -> 8990000 | E41: =SUBTOTAL(9,E29:E40) -> 1940000 | F41: =SUBTOTAL(9,F29:F40) -> 763000 | G41: =SUBTOTAL(9,G29:G40) -> 548000 | H41: =SUBTOTAL(9,H29:H40) -> 6010000 | I41: =SUBTOTAL(9,I29:I40) -> 3251000 | J41: =SUBTOTAL(9,J29:J40) -> 2759000
A42: 2024 | B42: Jan | C42: 1180000 | D42: 710000 | E42: 155000 | F42: 56000 | G42: 40000 | H42: ='CLEANED DATA'!$C42-'CLEANED DATA'!$D42 -> 470000 | I42: ='CLEANED DATA'!$E42+'CLEANED DATA'!$F42+'CLEANED DATA'!$G42 -> 251000 | J42: ='CLEANED DATA'!$C42-('CLEANED DATA'!$D42+'CLEANED DATA'!$I42) -> 219000 | K42: ='CLEANED DATA'!$J42/'CLEANED DATA'!$C42 -> 0.18559322 | L42: =('CLEANED DATA'!$C42-C40)/C40 -> -0.27160494
A43: 2024 | B43: Feb | C43: 1150000 | D43: 700000 | E43: 152000 | F43: 54000 | G43: 38000 | H43: ='CLEANED DATA'!$C43-'CLEANED DATA'!$D43 -> 450000 | I43: ='CLEANED DATA'!$E43+'CLEANED DATA'!$F43+'CLEANED DATA'!$G43 -> 244000 | J43: ='CLEANED DATA'!$C43-('CLEANED DATA'!$D43+'CLEANED DATA'!$I43) -> 206000 | K43: ='CLEANED DATA'!$J43/'CLEANED DATA'!$C43 -> 0.17913043 | L43: =('CLEANED DATA'!$C43-C42)/C42 -> -0.025423729
A44: 2024 | B44: Mar | C44: 1230000 | D44: 740000 | E44: 158000 | F44: 58000 | G44: 42000 | H44: ='CLEANED DATA'!$C44-'CLEANED DATA'!$D44 -> 490000 | I44: ='CLEANED DATA'!$E44+'CLEANED DATA'!$F44+'CLEANED DATA'!$G44 -> 258000 | J44: ='CLEANED DATA'!$C44-('CLEANED DATA'!$D44+'CLEANED DATA'!$I44) -> 232000 | K44: ='CLEANED DATA'!$J44/'CLEANED DATA'!$C44 -> 0.18861789 | L44: =('CLEANED DATA'!$C44-C43)/C43 -> 0.069565217
A45: 2024 | B45: Apr | C45: 1270000 | D45: 760000 | E45: 160000 | F45: 60000 | G45: 44000 | H45: ='CLEANED DATA'!$C45-'CLEANED DATA'!$D45 -> 510000 | I45: ='CLEANED DATA'!$E45+'CLEANED DATA'!$F45+'CLEANED DATA'!$G45 -> 264000 | J45: ='CLEANED DATA'!$C45-('CLEANED DATA'!$D45+'CLEANED DATA'!$I45) -> 246000 | K45: ='CLEANED DATA'!$J45/'CLEANED DATA'!$C45 -> 0.19370079 | L45: =('CLEANED DATA'!$C45-C44)/C44 -> 0.032520325
A46: 2024 | B46: May | C46: 1320000 | D46: 790000 | E46: 165000 | F46: 63000 | G46: 47000 | H46: ='CLEANED DATA'!$C46-'CLEANED DATA'!$D46 -> 530000 | I46: ='CLEANED DATA'!$E46+'CLEANED DATA'!$F46+'CLEANED DATA'!$G46 -> 275000 | J46: ='CLEANED DATA'!$C46-('CLEANED DATA'!$D46+'CLEANED DATA'!$I46) -> 255000 | K46: ='CLEANED DATA'!$J46/'CLEANED DATA'!$C46 -> 0.19318182 | L46: =('CLEANED DATA'!$C46-C45)/C45 -> 0.039370079
A47: 2024 | B47: Jun | C47: 1360000 | D47: 820000 | E47: 168000 | F47: 66000 | G47: 50000 | H47: ='CLEANED DATA'!$C47-'CLEANED DATA'!$D47 -> 540000 | I47: ='CLEANED DATA'!$E47+'CLEANED DATA'!$F47+'CLEANED DATA'!$G47 -> 284000 | J47: ='CLEANED DATA'!$C47-('CLEANED DATA'!$D47+'CLEANED DATA'!$I47) -> 256000 | K47: ='CLEANED DATA'!$J47/'CLEANED DATA'!$C47 -> 0.18823529 | L47: =('CLEANED DATA'!$C47-C46)/C46 -> 0.03030303
A48: 2024 | B48: Jul | C48: 1410000 | D48: 850000 | E48: 170000 | F48: 69000 | G48: 52000 | H48: ='CLEANED DATA'!$C48-'CLEANED DATA'!$D48 -> 560000 | I48: ='CLEANED DATA'!$E48+'CLEANED DATA'!$F48+'CLEANED DATA'!$G48 -> 291000 | J48: ='CLEANED DATA'!$C48-('CLEANED DATA'!$D48+'CLEANED DATA'!$I48) -> 269000 | K48: ='CLEANED DATA'!$J48/'CLEANED DATA'!$C48 -> 0.19078014 | L48: =('CLEANED DATA'!$C48-C47)/C47 -> 0.036764706
A49: 2024 | B49: Aug | C49: 1390000 | D49: 840000 | E49: 168000 | F49: 68000 | G49: 51000 | H49: ='CLEANED DATA'!$C49-'CLEANED DATA'!$D49 -> 550000 | I49: ='CLEANED DATA'!$E49+'CLEANED DATA'!$F49+'CLEANED DATA'!$G49 -> 287000 | J49: ='CLEANED DATA'!$C49-('CLEANED DATA'!$D49+'CLEANED DATA'!$I49) -> 263000 | K49: ='CLEANED DATA'!$J49/'CLEANED DATA'!$C49 -> 0.18920863 | L49: =('CLEANED DATA'!$C49-C48)/C48 -> -0.014184397
A50: 2024 | B50: Sep | C50: 1460000 | D50: 880000 | E50: 172000 | F50: 72000 | G50: 55000 | H50: ='CLEANED DATA'!$C50-'CLEANED DATA'!$D50 -> 580000 | I50: ='CLEANED DATA'!$E50+'CLEANED DATA'!$F50+'CLEANED DATA'!$G50 -> 299000 | J50: ='CLEANED DATA'!$C50-('CLEANED DATA'!$D50+'CLEANED DATA'!$I50) -> 281000 | K50: ='CLEANED DATA'!$J50/'CLEANED DATA'!$C50 -> 0.19246575 | L50: =('CLEANED DATA'!$C50-C49)/C49 -> 0.050359712
A51: 2024 | B51: Oct | C51: 1520000 | D51: 920000 | E51: 178000 | F51: 76000 | G51: 58000 | H51: ='CLEANED DATA'!$C51-'CLEANED DATA'!$D51 -> 600000 | I51: ='CLEANED DATA'!$E51+'CLEANED DATA'!$F51+'CLEANED DATA'!$G51 -> 312000 | J51: ='CLEANED DATA'!$C51-('CLEANED DATA'!$D51+'CLEANED DATA'!$I51) -> 288000 | K51: ='CLEANED DATA'!$J51/'CLEANED DATA'!$C51 -> 0.18947368 | L51: =('CLEANED DATA'!$C51-C50)/C50 -> 0.04109589
A52: 2024 | B52: Nov | C52: 1600000 | D52: 960000 | E52: 182000 | F52: 80000 | G52: 61000 | H52: ='CLEANED DATA'!$C52-'CLEANED DATA'!$D52 -> 640000 | I52: ='CLEANED DATA'!$E52+'CLEANED DATA'!$F52+'CLEANED DATA'!$G52 -> 323000 | J52: ='CLEANED DATA'!$C52-('CLEANED DATA'!$D52+'CLEANED DATA'!$I52) -> 317000 | K52: ='CLEANED DATA'!$J52/'CLEANED DATA'!$C52 -> 0.198125 | L52: =('CLEANED DATA'!$C52-C51)/C51 -> 0.052631579
A53: 2024 | B53: Dec | C53: 1780000 | D53: 1050000 | E53: 190000 | F53: 90000 | G53: 68000 | H53: ='CLEANED DATA'!$C53-'CLEANED DATA'!$D53 -> 730000 | I53: ='CLEANED DATA'!$E53+'CLEANED DATA'!$F53+'CLEANED DATA'!$G53 -> 348000 | J53: ='CLEANED DATA'!$C53-('CLEANED DATA'!$D53+'CLEANED DATA'!$I53) -> 382000 | K53: ='CLEANED DATA'!$J53/'CLEANED DATA'!$C53 -> 0.21460674 | L53: =('CLEANED DATA'!$C53-C52)/C52 -> 0.1125
A54: 2024 Total | C54: =SUBTOTAL(9,C42:C53) -> 16670000 | D54: =SUBTOTAL(9,D42:D53) -> 10020000 | E54: =SUBTOTAL(9,E42:E53) -> 2018000 | F54: =SUBTOTAL(9,F42:F53) -> 812000 | G54: =SUBTOTAL(9,G42:G53) -> 606000 | H54: =SUBTOTAL(9,H42:H53) -> 6650000 | I54: =SUBTOTAL(9,I42:I53) -> 3436000 | J54: =SUBTOTAL(9,J42:J53) -> 3214000
A55: 2025 | B55: Jan | C55: 1300000 | D55: 780000 | E55: 160000 | F55: 60000 | G55: 44000 | H55: ='CLEANED DATA'!$C55-'CLEANED DATA'!$D55 -> 520000 | I55: ='CLEANED DATA'!$E55+'CLEANED DATA'!$F55+'CLEANED DATA'!$G55 -> 264000 | J55: ='CLEANED DATA'!$C55-('CLEANED DATA'!$D55+'CLEANED DATA'!$I55) -> 256000 | K55: ='CLEANED DATA'!$J55/'CLEANED DATA'!$C55 -> 0.19692308 | L55: =('CLEANED DATA'!$C55-C53)/C53 -> -0.26966292
A56: 2025 | B56: Feb | C56: 1280000 | D56: 770000 | E56: 158000 | F56: 58000 | G56: 42000 | H56: ='CLEANED DATA'!$C56-'CLEANED DATA'!$D56 -> 510000 | I56: ='CLEANED DATA'!$E56+'CLEANED DATA'!$F56+'CLEANED DATA'!$G56 -> 258000 | J56: ='CLEANED DATA'!$C56-('CLEANED DATA'!$D56+'CLEANED DATA'!$I56) -> 252000 | K56: ='CLEANED DATA'!$J56/'CLEANED DATA'!$C56 -> 0.196875 | L56: =('CLEANED DATA'!$C56-C55)/C55 -> -0.015384615
A57: 2025 | B57: Mar | C57: 1350000 | D57: 810000 | E57: 162000 | F57: 62000 | G57: 46000 | H57: ='CLEANED DATA'!$C57-'CLEANED DATA'!$D57 -> 540000 | I57: ='CLEANED DATA'!$E57+'CLEANED DATA'!$F57+'CLEANED DATA'!$G57 -> 270000 | J57: ='CLEANED DATA'!$C57-('CLEANED DATA'!$D57+'CLEANED DATA'!$I57) -> 270000 | K57: ='CLEANED DATA'!$J57/'CLEANED DATA'!$C57 -> 0.2 | L57: =('CLEANED DATA'!$C57-C56)/C56 -> 0.0546875
A58: 2025 | B58: Apr | C58: 1400000 | D58: 840000 | E58: 165000 | F58: 65000 | G58: 48000 | H58: ='CLEANED DATA'!$C58-'CLEANED DATA'!$D58 -> 560000 | I58: ='CLEANED DATA'!$E58+'CLEANED DATA'!$F58+'CLEANED DATA'!$G58 -> 278000 | J58: ='CLEANED DATA'!$C58-('CLEANED DATA'!$D58+'CLEANED DATA'!$I58) -> 282000 | K58: ='CLEANED DATA'!$J58/'CLEANED DATA'!$C58 -> 0.20142857 | L58: =('CLEANED DATA'!$C58-C57)/C57 -> 0.037037037
A59: 2025 | B59: May | C59: 1450000 | D59: 870000 | E59: 168000 | F59: 68000 | G59: 51000 | H59: ='CLEANED DATA'!$C59-'CLEANED DATA'!$D59 -> 580000 | I59: ='CLEANED DATA'!$E59+'CLEANED DATA'!$F59+'CLEANED DATA'!$G59 -> 287000 | J59: ='CLEANED DATA'!$C59-('CLEANED DATA'!$D59+'CLEANED DATA'!$I59) -> 293000 | K59: ='CLEANED DATA'!$J59/'CLEANED DATA'!$C59 -> 0.20206897 | L59: =('CLEANED DATA'!$C59-C58)/C58 -> 0.035714286
A60: 2025 | B60: Jun | C60: 1600000 | D60: 900000 | E60: 150000 | F60: 71000 | G60: 54000 | H60: ='CLEANED DATA'!$C60-'CLEANED DATA'!$D60 -> 700000 | I60: ='CLEANED DATA'!$E60+'CLEANED DATA'!$F60+'CLEANED DATA'!$G60 -> 275000 | J60: ='CLEANED DATA'!$C60-('CLEANED DATA'!$D60+'CLEANED DATA'!$I60) -> 425000 | K60: ='CLEANED DATA'!$J60/'CLEANED DATA'!$C60 -> 0.265625 | L60: =('CLEANED DATA'!$C60-C59)/C59 -> 0.10344828
A61: 2025 | B61: Jul | C61: 980000 | D61: 590000 | E61: 152000 | F61: 52000 | G61: 35000 | H61: ='CLEANED DATA'!$C61-'CLEANED DATA'!$D61 -> 390000 | I61: ='CLEANED DATA'!$E61+'CLEANED DATA'!$F61+'CLEANED DATA'!$G61 -> 239000 | J61: ='CLEANED DATA'!$C61-('CLEANED DATA'!$D61+'CLEANED DATA'!$I61) -> 151000 | K61: ='CLEANED DATA'!$J61/'CLEANED DATA'!$C61 -> 0.15408163 | L61: =('CLEANED DATA'!$C61-C60)/C60 -> -0.3875
A62: 2025 | B62: Aug | C62: 960000 | D62: 580000 | E62: 150000 | F62: 51000 | G62: 34000 | H62: ='CLEANED DATA'!$C62-'CLEANED DATA'!$D62 -> 380000 | I62: ='CLEANED DATA'!$E62+'CLEANED DATA'!$F62+'CLEANED DATA'!$G62 -> 235000 | J62: ='CLEANED DATA'!$C62-('CLEANED DATA'!$D62+'CLEANED DATA'!$I62) -> 145000 | K62: ='CLEANED DATA'!$J62/'CLEANED DATA'!$C62 -> 0.15104167 | L62: =('CLEANED DATA'!$C62-C61)/C61 -> -0.020408163
A63: 2025 | B63: Sep | C63: 1020000 | D63: 610000 | E63: 155000 | F63: 54000 | G63: 36000 | H63: ='CLEANED DATA'!$C63-'CLEANED DATA'!$D63 -> 410000 | I63: ='CLEANED DATA'!$E63+'CLEANED DATA'!$F63+'CLEANED DATA'!$G63 -> 245000 | J63: ='CLEANED DATA'!$C63-('CLEANED DATA'!$D63+'CLEANED DATA'!$I63) -> 165000 | K63: ='CLEANED DATA'!$J63/'CLEANED DATA'!$C63 -> 0.16176471 | L63: =('CLEANED DATA'!$C63-C62)/C62 -> 0.0625
A64: 2025 | B64: Oct | C64: 1520000 | D64: 920000 | E64: 178000 | F64: 76000 | G64: 58000 | H64: ='CLEANED DATA'!$C64-'CLEANED DATA'!$D64 -> 600000 | I64: ='CLEANED DATA'!$E64+'CLEANED DATA'!$F64+'CLEANED DATA'!$G64 -> 312000 | J64: ='CLEANED DATA'!$C64-('CLEANED DATA'!$D64+'CLEANED DATA'!$I64) -> 288000 | K64: ='CLEANED DATA'!$J64/'CLEANED DATA'!$C64 -> 0.18947368 | L64: =('CLEANED DATA'!$C64-C63)/C63 -> 0.49019608
A65: 2025 | B65: Nov | C65: 1600000 | D65: 960000 | E65: 182000 | F65: 80000 | G65: 61000 | H65: ='CLEANED DATA'!$C65-'CLEANED DATA'!$D65 -> 640000 | I65: ='CLEANED DATA'!$E65+'CLEANED DATA'!$F65+'CLEANED DATA'!$G65 -> 323000 | J65: ='CLEANED DATA'!$C65-('CLEANED DATA'!$D65+'CLEANED DATA'!$I65) -> 317000 | K65: ='CLEANED DATA'!$J65/'CLEANED DATA'!$C65 -> 0.198125 | L65: =('CLEANED DATA'!$C65-C64)/C64 -> 0.052631579
A66: 2025 | B66: Dec | C66: 1740000 | D66: 1090000 | E66: 190000 | F66: 95000 | G66: 70000 | H66: ='CLEANED DATA'!$C66-'CLEANED DATA'!$D66 -> 650000 | I66: ='CLEANED DATA'!$E66+'CLEANED DATA'!$F66+'CLEANED DATA'!$G66 -> 355000 | J66: ='CLEANED DATA'!$C66-('CLEANED DATA'!$D66+'CLEANED DATA'!$I66) -> 295000 | K66: ='CLEANED DATA'!$J66/'CLEANED DATA'!$C66 -> 0.16954023 | L66: =('CLEANED DATA'!$C66-C65)/C65 -> 0.0875
A67: 2025 Total | C67: =SUBTOTAL(9,C55:C66) -> 16200000 | D67: =SUBTOTAL(9,D55:D66) -> 9720000 | E67: =SUBTOTAL(9,E55:E66) -> 1970000 | F67: =SUBTOTAL(9,F55:F66) -> 792000 | G67: =SUBTOTAL(9,G55:G66) -> 579000 | H67: =SUBTOTAL(9,H55:H66) -> 6480000 | I67: =SUBTOTAL(9,I55:I66) -> 3341000 | J67: =SUBTOTAL(9,J55:J66) -> 3139000
A68: Grand Total | C68: =SUBTOTAL(9,C3:C66) -> 73130000 | D68: =SUBTOTAL(9,D3:D66) -> 43915000 | E68: =SUBTOTAL(9,E3:E66) -> 9646000 | F68: =SUBTOTAL(9,F3:F66) -> 3700000 | G68: =SUBTOTAL(9,G3:G66) -> 2634500 | H68: =SUBTOTAL(9,H3:H66) -> 29215000 | I68: =SUBTOTAL(9,I3:I66) -> 15980500 | J68: =SUBTOTAL(9,J3:J66) -> 13234500

Sheet RAW DATA
A1: LIZZY ELECTRONICS
A2: Year | B2: Month | C2: Revenue | D2: Cost Of Goods Sold | E2: Operating Expenses | F2: Marketing Expenses | G2: Other Expenses
A3: 2021 | B3: Jan | C3: 850000 | D3: 510000 | E3: 140000 | F3: 45000 | G3: 30000
A4: 2021 | B4: Feb | C4: 820000 | D4: 500000 | E4: 138000 | F4: 42000 | G4: 28000
A5: 2021 | B5: Mar | C5: 900000 | D5: 540000 | E5: 145000 | F5: 47000 | G5: 31000
A6: 2021 | B6: Apr | C6: 870000 | D6: 525000 | E6: 142000 | F6: 46000 | G6: 29500
A7: 2021 | B7: May | C7: 920000 | D7: 550000 | E7: 148000 | F7: 48000 | G7: 32000
A8: 2021 | B8: Jun | C8: 950000 | D8: 570000 | E8: 150000 | F8: 50000 | G8: 33000
A9: 2021 | B9: Jul | C9: 980000 | D9: 590000 | E9: 152000 | F9: 52000 | G9: 35000
A10: 2021 | B10: Aug | C10: 960000 | D10: 580000 | E10: 150000 | F10: 51000 | G10: 34000
A11: 2021 | B11: Sep | C11: 1020000 | D11: 610000 | E11: 155000 | F11: 54000 | G11: 36000
A12: 2021 | B12: Oct | C12: 1080000 | D12: 650000 | E12: 160000 | F12: 58000 | G12: 38000
A13: 2021 | B13: Nov | C13: 1150000 | D13: 690000 | E13: 165000 | F13: 62000 | G13: 40000
A14: 2021 | B14: Dec | C14: 1300000 | D14: 780000 | E14: 175000 | F14: 70000 | G14: 45000
... A62: 2025 | B62: Dec | C62: 1740000 | D62: 1090000 | E62: 190000 | F62: 95000 | G62: 70000

Sheet PIVOT TABLES
B3: Month | C3: Average of Monthly Growth Rate % | E3: Month | F3: Total Revenue | G3: Total Net Profit | I3: Year | J3: Sum of Other Expenses | K3: Sum of Marketing Expenses | L3: Sum of Operating Expenses
B4: Jan | C4: -0.28102902 | E4: Jan | F4: 5300000 | G4: 928000 | I4: 2021 | J4: 411500 | K4: 625000 | L4: 1820000
B5: Feb | C5: -0.025282604 | E5: Feb | F5: 5170000 | G5: 881000 | I5: 2022 | J5: 490000 | K5: 708000 | L5: 1898000
B6: Mar | C6: 0.077826791 | E6: Mar | F6: 5560000 | G6: 994000 | I6: 2023 | J6: 548000 | K6: 763000 | L6: 1940000
B7: Apr | C7: 0.020639982 | E7: Apr | F7: 5690000 | G7: 1026500 | I7: 2024 | J7: 606000 | K7: 812000 | L7: 2018000
B8: May | C8: 0.04342966 | E8: May | F8: 5930000 | G8: 1073000 | I8: 2025 | J8: 579000 | K8: 792000 | L8: 1970000
B9: Jun | C9: 0.047598831 | E9: Jun | F9: 6230000 | G9: 1236000
B10: Jul | C10: -0.048361821 | E10: Jul | F10: 5780000 | G10: 995000
B11: Aug | C11: -0.017658523 | E11: Aug | F11: 5680000 | G11: 965000
B12: Sep | C12: 0.056986228 | E12: Sep | F12: 6000000 | G12: 1059000
B13: Oct | C13: 0.13897842 | E13: Oct | F13: 6750000 | G13: 1222000
B14: Nov | C14: 0.055360522 | E14: Nov | F14: 7120000 | G14: 1336000
B15: Dec | C15: 0.11377766 | E15: Dec | F15: 7920000 | G15: 1519000
B17: Month | C17: Total Net Profit Margin % | E17: Revenue | F17: Total Expenses
B18: Jan | C18: 0.86160411 | E18: 850000 | F18: 215000
B19: Feb | C19: 0.83618557 | E19: 820000 | F19: 208000
B20: Mar | C20: 0.88126682 | E20: 900000 | F20: 223000
B21: Apr | C21: 0.88541046 | E21: 870000 | F21: 217500
B22: May | C22: 0.89067632 | E22: 920000 | F22: 228000
B23: Jun | C23: 0.95947642 | E23: 950000 | F23: 233000
B24: Jul | C24: 0.84968246 | E24: 980000 | F24: 239000
B25: Aug | C25: 0.83779197 | E25: 960000 | F25: 235000
B26: Sep | C26: 0.87345536 | E26: 1020000 | F26: 245000
B27: Oct | C27: 0.89844109 | E27: 1080000 | F27: 256000
B28: Nov | C28: 0.93113983 | E28: 1150000 | F28: 267000
B29: Dec | C29: 0.95543108 | E29: 1300000 | F29: 290000
E30: 920000 | F30: 224000
E31: 900000 | F31: 217000
E32: 980000 | F32: 231000
E33: 1010000 | F33: 238000
E34: 1060000 | F34: 248000
E35: 1100000 | F35: 256000
E36: 1140000 | F36: 262000
E37: 1120000 | F37: 258000
E38: 1180000 | F38: 269000
E39: 1250000 | F39: 283000
E40: 1320000 | F40: 294000
E41: 1480000 | F41: 316000
... E77: 1740000 | F77: 355000

Sheet CHARTS
C1: Correlation Analysis
D2: Revenue | E2: Total Expenses
C3: Revenue | D3: 1
C4: Total Expenses | D4: 0.9588703 | E4: 1
C6: Revenue and total expenses show a strong positive correlation (r=0.96), indicating that cost structures scale closely with revenue growth.
C7: This suggests the need for expense efficiency to improve profit margins.
J23: Revenue remains consistently higher as it represents total inflows
J24: while Net Profit is lower due to cost structures and operational expenses reducing retained earnings.
